MANIFEST.in
README.txt
setup.cfg
setup.py
docs/HISTORY.txt
raptus/__init__.py
raptus.portlet.multilanguage.egg-info/PKG-INFO
raptus.portlet.multilanguage.egg-info/SOURCES.txt
raptus.portlet.multilanguage.egg-info/dependency_links.txt
raptus.portlet.multilanguage.egg-info/entry_points.txt
raptus.portlet.multilanguage.egg-info/namespace_packages.txt
raptus.portlet.multilanguage.egg-info/not-zip-safe
raptus.portlet.multilanguage.egg-info/requires.txt
raptus.portlet.multilanguage.egg-info/top_level.txt
raptus/portlet/__init__.py
raptus/portlet/multilanguage/__init__.py
raptus/portlet/multilanguage/configure.zcml
raptus/portlet/multilanguage/multilanguage.pt
raptus/portlet/multilanguage/multilanguage.py
raptus/portlet/multilanguage/locales/plone.pot
raptus/portlet/multilanguage/locales/de/LC_MESSAGES/plone.mo
raptus/portlet/multilanguage/locales/de/LC_MESSAGES/plone.po
raptus/portlet/multilanguage/locales/fr/LC_MESSAGES/plone.mo
raptus/portlet/multilanguage/locales/fr/LC_MESSAGES/plone.po
raptus/portlet/multilanguage/profiles/default/portlets.xml