Metadata-Version: 1.0
Name: raptus.portlet.multilanguage
Version: 1.0
Summary: Provides a static text portlet for which one may select the language for which the portlet is available
Home-page: https://svn.plone.org/svn/collective/raptus.portlet.multilanguage
Author: Raptus AG
Author-email: dev@raptus.com
License: GPL
Platform: UNKNOWN
Classifier: Programming Language :: Python
Classifier: Topic :: Software Development :: Libraries :: Python Modules
